{
  "labels": [
    "Australia",
    "China",
    "Japan",
    "Bahrain",
    "Saudi Arabia",
    "Miami",
    "Emilia-Romagna",
    "Monaco",
    "Spain",
    "Canada",
    "Austria",
    "Great Britain",
    "Belgium",
    "Hungary",
    "Netherlands",
    "Italy",
    "Azerbaijan",
    "Singapore",
    "United States",
    "Mexico",
    "Brazil",
    "Las Vegas",
    "Qatar",
    "Abu Dhabi"
  ],
  "series": [
    {
      "title": "Max Verstappen",
      "data": [
        18,
        36,
        61,
        69,
        87,
        99,
        99,
        99,
        99,
        99,
        99,
        99,
        99,
        99,
        99,
        99,
        99,
        99,
        99,
        99,
        99,
        99,
        99,
        99
      ],
      "color": "#0600EF"
    },
    {
      "title": "Yuki Tsunoda",
      "data": [
        0,
        3,
        3,
        5,
        5,
        9,
        9,
        9,
        9,
        9,
        9,
        9,
        9,
        9,
        9,
        9,
        9,
        9,
        9,
        9,
        9,
        9,
        9,
        9
      ],
      "color": "#0600EF"
    },
    {
      "title": "George Russell",
      "data": [
        15,
        35,
        45,
        63,
        73,
        93,
        93,
        93,
        93,
        93,
        93,
        93,
        93,
        93,
        93,
        93,
        93,
        93,
        93,
        93,
        93,
        93,
        93,
        93
      ],
      "color": "#00D2BE"
    },
    {
      "title": "Andrea Kimi Antonelli",
      "data": [
        12,
        22,
        30,
        30,
        38,
        48,
        48,
        48,
        48,
        48,
        48,
        48,
        48,
        48,
        48,
        48,
        48,
        48,
        48,
        48,
        48,
        48,
        48,
        48
      ],
      "color": "#00D2BE"
    },
    {
      "title": "Charles Leclerc",
      "data": [
        4,
        8,
        20,
        32,
        47,
        53,
        53,
        53,
        53,
        53,
        53,
        53,
        53,
        53,
        53,
        53,
        53,
        53,
        53,
        53,
        53,
        53,
        53,
        53
      ],
      "color": "#DC0000"
    },
    {
      "title": "Lewis Hamilton",
      "data": [
        1,
        9,
        15,
        25,
        31,
        41,
        41,
        41,
        41,
        41,
        41,
        41,
        41,
        41,
        41,
        41,
        41,
        41,
        41,
        41,
        41,
        41,
        41,
        41
      ],
      "color": "#DC0000"
    },
    {
      "title": "Lando Norris",
      "data": [
        25,
        44,
        62,
        77,
        89,
        115,
        115,
        115,
        115,
        115,
        115,
        115,
        115,
        115,
        115,
        115,
        115,
        115,
        115,
        115,
        115,
        115,
        115,
        115
      ],
      "color": "#FF8700"
    },
    {
      "title": "Oscar Piastri",
      "data": [
        2,
        34,
        49,
        74,
        99,
        131,
        131,
        131,
        131,
        131,
        131,
        131,
        131,
        131,
        131,
        131,
        131,
        131,
        131,
        131,
        131,
        131,
        131,
        131
      ],
      "color": "#FF8700"
    },
    {
      "title": "Fernando Alonso",
      "data": [
        0,
        0,
        0,
        0,
        0,
        0,
        0,
        0,
        0,
        0,
        0,
        0,
        0,
        0,
        0,
        0,
        0,
        0,
        0,
        0,
        0,
        0,
        0,
        0
      ],
      "color": "#006F62"
    },
    {
      "title": "Lance Stroll",
      "data": [
        8,
        10,
        10,
        10,
        10,
        14,
        14,
        14,
        14,
        14,
        14,
        14,
        14,
        14,
        14,
        14,
        14,
        14,
        14,
        14,
        14,
        14,
        14,
        14
      ],
      "color": "#006F62"
    },
    {
      "title": "Alexander Albon",
      "data": [
        10,
        16,
        18,
        18,
        20,
        30,
        30,
        30,
        30,
        30,
        30,
        30,
        30,
        30,
        30,
        30,
        30,
        30,
        30,
        30,
        30,
        30,
        30,
        30
      ],
      "color": "#00A0DE"
    },
    {
      "title": "Carlos Sainz",
      "data": [
        0,
        1,
        1,
        1,
        5,
        7,
        7,
        7,
        7,
        7,
        7,
        7,
        7,
        7,
        7,
        7,
        7,
        7,
        7,
        7,
        7,
        7,
        7,
        7
      ],
      "color": "#00A0DE"
    },
    {
      "title": "Pierre Gasly",
      "data": [
        0,
        0,
        0,
        6,
        6,
        7,
        7,
        7,
        7,
        7,
        7,
        7,
        7,
        7,
        7,
        7,
        7,
        7,
        7,
        7,
        7,
        7,
        7,
        7
      ],
      "color": "#0090FF"
    },
    {
      "title": "Jack Doohan",
      "data": [
        0,
        0,
        0,
        0,
        0,
        0,
        0,
        0,
        0,
        0,
        0,
        0,
        0,
        0,
        0,
        0,
        0,
        0,
        0,
        0,
        0,
        0,
        0,
        0
      ],
      "color": "#0090FF"
    },
    {
      "title": "Liam Lawson",
      "data": [
        0,
        0,
        0,
        0,
        0,
        0,
        0,
        0,
        0,
        0,
        0,
        0,
        0,
        0,
        0,
        0,
        0,
        0,
        0,
        0,
        0,
        0,
        0,
        0
      ],
      "color": "#2B4562"
    },
    {
      "title": "Isack Hadjar",
      "data": [
        0,
        0,
        4,
        4,
        5,
        5,
        5,
        5,
        5,
        5,
        5,
        5,
        5,
        5,
        5,
        5,
        5,
        5,
        5,
        5,
        5,
        5,
        5,
        5
      ],
      "color": "#2B4562"
    },
    {
      "title": "Esteban Ocon",
      "data": [
        0,
        10,
        10,
        14,
        14,
        14,
        14,
        14,
        14,
        14,
        14,
        14,
        14,
        14,
        14,
        14,
        14,
        14,
        14,
        14,
        14,
        14,
        14,
        14
      ],
      "color": "#FFFFFF"
    },
    {
      "title": "Oliver Bearman",
      "data": [
        0,
        4,
        5,
        6,
        6,
        6,
        6,
        6,
        6,
        6,
        6,
        6,
        6,
        6,
        6,
        6,
        6,
        6,
        6,
        6,
        6,
        6,
        6,
        6
      ],
      "color": "#FFFFFF"
    },
    {
      "title": "Nico Hülkenberg",
      "data": [
        6,
        6,
        6,
        6,
        6,
        6,
        6,
        6,
        6,
        6,
        6,
        6,
        6,
        6,
        6,
        6,
        6,
        6,
        6,
        6,
        6,
        6,
        6,
        6
      ],
      "color": "#00e701"
    },
    {
      "title": "Gabriel Bortoletto",
      "data": [
        0,
        0,
        0,
        0,
        0,
        0,
        0,
        0,
        0,
        0,
        0,
        0,
        0,
        0,
        0,
        0,
        0,
        0,
        0,
        0,
        0,
        0,
        0,
        0
      ],
      "color": "#00e701"
    }
    
  ]
}